icelander_generator/__init__.py
icelander_generator/address.py
icelander_generator/name_scraper.py
icelander_generator/rejects.json
icelander_generator/data/icelandic_names.json
icelander_generator/data/po_codes.tsv
icelander_generator/data/streets.tsv
icelander_generator-0.3.2.dist-info/METADATA
icelander_generator-0.3.2.dist-info/WHEEL
icelander_generator-0.3.2.dist-info/top_level.txt
icelander_generator-0.3.2.dist-info/RECORD
