Metadata-Version: 2.1
Name: icelander-generator
Version: 0.3.2
Summary: A utility to generate random Icelanders
Home-page: https://github.com/7oi/IcelanderGenerator
Author: 7oi
Author-email: 7oi@7oi.is
License: MIT
Keywords: tests,generator
Platform: UNKNOWN
Requires-Dist: lxml
Requires-Dist: requests
Requires-Dist: kennitala
Requires-Dist: future
